fds/__init__.py
fds/protobuf/__init__.py
fds/protobuf/stach/__init__.py
fds/protobuf/stach/v3/Column_pb2.py
fds/protobuf/stach/v3/MetadataItem_pb2.py
fds/protobuf/stach/v3/RowOrganizedTable_pb2.py
fds/protobuf/stach/v3/TableView_pb2.py
fds/protobuf/stach/v3/Table_pb2.py
fds/protobuf/stach/v3/Views_pb2.py
fds/protobuf/stach/v3/__init__.py
fds.protobuf.stach.v3-1.0.0.dist-info/METADATA
fds.protobuf.stach.v3-1.0.0.dist-info/WHEEL
fds.protobuf.stach.v3-1.0.0.dist-info/top_level.txt
fds.protobuf.stach.v3-1.0.0.dist-info/RECORD
